<annotation>
  <folder>VOC2012</folder>
  <filename>002037.jpg</filename>
  <source>
    <database>The LabelMe Object Detection Database</database>
  </source>
  <size>
    <width>1280</width>
    <height>720</height>
    <depth>3</depth>
  </size>
  <object>
    <name>car</name>
    <pose>Unspecified</pose>
    <truncated>0</truncated>
    <difficult>1</difficult>
    <bndbox>
      <xmin>567</xmin>
      <ymin>163</ymin>
      <xmax>601</xmax>
      <ymax>185</ymax>
    </bndbox>
  </object>
  <object>
    <name>car</name>
    <pose>Unspecified</pose>
    <truncated>0</truncated>
    <difficult>1</difficult>
    <bndbox>
      <xmin>619</xmin>
      <ymin>160</ymin>
      <xmax>650</xmax>
      <ymax>186</ymax>
    </bndbox>
  </object>
  <object>
    <name>car</name>
    <pose>Unspecified</pose>
    <truncated>0</truncated>
    <difficult>1</difficult>
    <bndbox>
      <xmin>667</xmin>
      <ymin>161</ymin>
      <xmax>687</xmax>
      <ymax>180</ymax>
    </bndbox>
  </object>
  <object>
    <name>car</name>
    <pose>Unspecified</pose>
    <truncated>0</truncated>
    <difficult>1</difficult>
    <bndbox>
      <xmin>898</xmin>
      <ymin>192</ymin>
      <xmax>940</xmax>
      <ymax>215</ymax>
    </bndbox>
  </object>
  <object>
    <name>car</name>
    <pose>Unspecified</pose>
    <truncated>0</truncated>
    <difficult>1</difficult>
    <bndbox>
      <xmin>947</xmin>
      <ymin>203</ymin>
      <xmax>984</xmax>
      <ymax>228</ymax>
    </bndbox>
  </object>
  <object>
    <name>car</name>
    <pose>Unspecified</pose>
    <truncated>0</truncated>
    <difficult>1</difficult>
    <bndbox>
      <xmin>1020</xmin>
      <ymin>225</ymin>
      <xmax>1066</xmax>
      <ymax>262</ymax>
    </bndbox>
  </object>
  <object>
    <name>car</name>
    <pose>Unspecified</pose>
    <truncated>0</truncated>
    <difficult>1</difficult>
    <bndbox>
      <xmin>1117</xmin>
      <ymin>250</ymin>
      <xmax>1192</xmax>
      <ymax>319</ymax>
    </bndbox>
  </object>
  <object>
    <name>rear</name>
    <pose>Unspecified</pose>
    <truncated>0</truncated>
    <difficult>0</difficult>
    <bndbox>
      <xmin>1118</xmin>
      <ymin>270</ymin>
      <xmax>1127</xmax>
      <ymax>287</ymax>
    </bndbox>
  </object>
  <object>
    <name>front</name>
    <pose>Unspecified</pose>
    <truncated>0</truncated>
    <difficult>0</difficult>
    <bndbox>
      <xmin>1151</xmin>
      <ymin>289</ymin>
      <xmax>1165</xmax>
      <ymax>307</ymax>
    </bndbox>
  </object>
</annotation>