<annotation>
  <folder>VOC2012</folder>
  <filename>002854.jpg</filename>
  <source>
    <database>The LabelMe Object Detection Database</database>
  </source>
  <size>
    <width>1280</width>
    <height>720</height>
    <depth>3</depth>
  </size>
  <object>
    <name>car</name>
    <pose>Unspecified</pose>
    <truncated>0</truncated>
    <difficult>0</difficult>
    <bndbox>
      <xmin>399</xmin>
      <ymin>135</ymin>
      <xmax>546</xmax>
      <ymax>230</ymax>
    </bndbox>
  </object>
  <object>
    <name>truck</name>
    <pose>Unspecified</pose>
    <truncated>0</truncated>
    <difficult>0</difficult>
    <bndbox>
      <xmin>532</xmin>
      <ymin>2</ymin>
      <xmax>743</xmax>
      <ymax>213</ymax>
    </bndbox>
  </object>
  <object>
    <name>car</name>
    <pose>Unspecified</pose>
    <truncated>0</truncated>
    <difficult>1</difficult>
    <bndbox>
      <xmin>709</xmin>
      <ymin>145</ymin>
      <xmax>810</xmax>
      <ymax>203</ymax>
    </bndbox>
  </object>
  <object>
    <name>bus</name>
    <pose>Unspecified</pose>
    <truncated>0</truncated>
    <difficult>0</difficult>
    <bndbox>
      <xmin>850</xmin>
      <ymin>53</ymin>
      <xmax>1277</xmax>
      <ymax>404</ymax>
    </bndbox>
  </object>
  <object>
    <name>rear</name>
    <pose>Unspecified</pose>
    <truncated>0</truncated>
    <difficult>0</difficult>
    <bndbox>
      <xmin>494</xmin>
      <ymin>184</ymin>
      <xmax>517</xmax>
      <ymax>222</ymax>
    </bndbox>
  </object>
  <object>
    <name>front</name>
    <pose>Unspecified</pose>
    <truncated>0</truncated>
    <difficult>0</difficult>
    <bndbox>
      <xmin>531</xmin>
      <ymin>180</ymin>
      <xmax>546</xmax>
      <ymax>205</ymax>
    </bndbox>
  </object>
  <object>
    <name>rear</name>
    <pose>Unspecified</pose>
    <truncated>0</truncated>
    <difficult>0</difficult>
    <bndbox>
      <xmin>728</xmin>
      <ymin>174</ymin>
      <xmax>742</xmax>
      <ymax>203</ymax>
    </bndbox>
  </object>
  <object>
    <name>front</name>
    <pose>Unspecified</pose>
    <truncated>0</truncated>
    <difficult>0</difficult>
    <bndbox>
      <xmin>919</xmin>
      <ymin>182</ymin>
      <xmax>980</xmax>
      <ymax>249</ymax>
    </bndbox>
  </object>
</annotation>